[
    {
        "maxAge": 86400,
        "priceHint": 4,
        "previousClose": 1.1750882,
        "open": 1.17495,
        "dayLow": 1.172333,
        "dayHigh": 1.1761938,
        "regularMarketPreviousClose": 1.1750882,
        "regularMarketOpen": 1.17495,
        "regularMarketDayLow": 1.172333,
        "regularMarketDayHigh": 1.1761938,
        "volume": 0,
        "regularMarketVolume": 0,
        "averageVolume": 0,
        "averageVolume10days": 0,
        "averageDailyVolume10Day": 0,
        "bid": 1.1748121,
        "ask": 1.1741223,
        "bidSize": 0,
        "askSize": 0,
        "fiftyTwoWeekLow": 1.0183818,
        "fiftyTwoWeekHigh": 1.1872959,
        "allTimeHigh": 13.717,
        "allTimeLow": 0.6239,
        "fiftyDayAverage": 1.1630296,
        "twoHundredDayAverage": 1.1522641,
        "currency": "USD",
        "tradeable": false,
        "quoteType": "CURRENCY",
        "symbol": "EURUSD=X",
        "language": "en-US",
        "region": "US",
        "typeDisp": "Currency",
        "quoteSourceName": "Delayed Quote",
        "triggerable": true,
        "customPriceAlertConfidence": "HIGH",
        "shortName": "EUR/USD",
        "longName": "EUR/USD",
        "regularMarketChangePercent": -0.023493137,
        "regularMarketPrice": 1.1748121,
        "regularMarketChange": -0.00027608871,
        "marketState": "REGULAR",
        "corporateActions": [],
        "regularMarketTime": 1767197877,
        "exchange": "CCY",
        "messageBoardId": "finmb_EUR_X",
        "exchangeTimezoneName": "Europe/London",
        "exchangeTimezoneShortName": "GMT",
        "gmtOffSetMilliseconds": 0,
        "market": "ccy_market",
        "esgPopulated": false,
        "sourceInterval": 15,
        "exchangeDataDelayedBy": 0,
        "cryptoTradeable": false,
        "hasPrePostMarketData": false,
        "firstTradeDateMilliseconds": 1070236800000,
        "regularMarketDayRange": "1.172333 - 1.1761938",
        "fullExchangeName": "CCY",
        "averageDailyVolume3Month": 0,
        "fiftyTwoWeekLowChange": 0.008949995,
        "fiftyTwoWeekLowChangePercent": 0.008788447,
        "fiftyTwoWeekRange": "1.0183818 - 1.1872959",
        "fiftyTwoWeekHighChange": -0.13075,
        "fiftyTwoWeekHighChangePercent": -0.11012419,
        "fiftyTwoWeekChangePercent": -12.070269,
        "fiftyDayAverageChange": -0.008623421,
        "fiftyDayAverageChangePercent": -0.007414619,
        "twoHundredDayAverageChange": -0.016656637,
        "twoHundredDayAverageChangePercent": -0.014455572,
        "trailingPegRatio": null
    },
    {
        "maxAge": 86400,
        "priceHint": 4,
        "previousClose": 156.364,
        "open": 156.336,
        "dayLow": 156.318,
        "dayHigh": 156.994,
        "regularMarketPreviousClose": 156.364,
        "regularMarketOpen": 156.336,
        "regularMarketDayLow": 156.318,
        "regularMarketDayHigh": 156.994,
        "volume": 0,
        "regularMarketVolume": 0,
        "averageVolume": 0,
        "averageVolume10days": 0,
        "averageDailyVolume10Day": 0,
        "bid": 156.73,
        "ask": 156.737,
        "bidSize": 0,
        "askSize": 0,
        "fiftyTwoWeekLow": 139.892,
        "fiftyTwoWeekHigh": 158.857,
        "allTimeHigh": 161.942,
        "allTimeLow": 75.57,
        "fiftyDayAverage": 154.93628,
        "twoHundredDayAverage": 148.72842,
        "currency": "JPY",
        "tradeable": false,
        "quoteType": "CURRENCY",
        "symbol": "JPY=X",
        "language": "en-US",
        "region": "US",
        "typeDisp": "Currency",
        "quoteSourceName": "Delayed Quote",
        "triggerable": true,
        "customPriceAlertConfidence": "HIGH",
        "shortName": "USD/JPY",
        "longName": "USD/JPY",
        "regularMarketChangePercent": 0.23278764,
        "regularMarketPrice": 156.728,
        "regularMarketChange": 0.3639984,
        "corporateActions": [],
        "regularMarketTime": 1767197913,
        "exchange": "CCY",
        "messageBoardId": "finmb_JPY_X",
        "exchangeTimezoneName": "Europe/London",
        "exchangeTimezoneShortName": "GMT",
        "gmtOffSetMilliseconds": 0,
        "market": "ccy_market",
        "esgPopulated": false,
        "fiftyTwoWeekLowChange": 16.835999,
        "fiftyTwoWeekLowChangePercent": 0.12034997,
        "fiftyTwoWeekRange": "139.892 - 158.857",
        "fiftyTwoWeekHighChange": -2.1289978,
        "fiftyTwoWeekHighChangePercent": -0.013401977,
        "fiftyTwoWeekChangePercent": -1.0816693,
        "fiftyDayAverageChange": 1.7917175,
        "fiftyDayAverageChangePercent": 0.011564222,
        "twoHundredDayAverageChange": 7.9995728,
        "twoHundredDayAverageChangePercent": 0.05378644,
        "sourceInterval": 15,
        "exchangeDataDelayedBy": 0,
        "cryptoTradeable": false,
        "marketState": "REGULAR",
        "hasPrePostMarketData": false,
        "firstTradeDateMilliseconds": 846633600000,
        "regularMarketDayRange": "156.318 - 156.994",
        "fullExchangeName": "CCY",
        "averageDailyVolume3Month": 0,
        "trailingPegRatio": null
    },
    {
        "maxAge": 86400,
        "priceHint": 4,
        "previousClose": 1.3467107,
        "open": 1.3467832,
        "dayLow": 1.340285,
        "dayHigh": 1.3476363,
        "regularMarketPreviousClose": 1.3467107,
        "regularMarketOpen": 1.3467832,
        "regularMarketDayLow": 1.340285,
        "regularMarketDayHigh": 1.3476363,
        "volume": 0,
        "regularMarketVolume": 0,
        "averageVolume": 0,
        "averageVolume10days": 0,
        "averageDailyVolume10Day": 0,
        "bid": 1.3456234,
        "ask": 1.3455328,
        "bidSize": 0,
        "askSize": 0,
        "fiftyTwoWeekLow": 1.2101264,
        "fiftyTwoWeekHigh": 1.378873,
        "allTimeHigh": 1.5689,
        "allTimeLow": 0.47263,
        "fiftyDayAverage": 1.326512,
        "twoHundredDayAverage": 1.3360732,
        "currency": "USD",
        "tradeable": false,
        "quoteType": "CURRENCY",
        "symbol": "GBPUSD=X",
        "language": "en-US",
        "region": "US",
        "typeDisp": "Currency",
        "quoteSourceName": "Delayed Quote",
        "triggerable": true,
        "customPriceAlertConfidence": "HIGH",
        "regularMarketChangePercent": -0.08073475,
        "regularMarketPrice": 1.3456234,
        "shortName": "GBP/USD",
        "longName": "GBP/USD",
        "regularMarketChange": -0.0010873079,
        "exchange": "CCY",
        "messageBoardId": "finmb_GBP_X",
        "exchangeTimezoneName": "Europe/London",
        "exchangeTimezoneShortName": "GMT",
        "gmtOffSetMilliseconds": 0,
        "market": "ccy_market",
        "esgPopulated": false,
        "corporateActions": [],
        "regularMarketTime": 1767197877,
        "marketState": "REGULAR",
        "twoHundredDayAverageChange": -0.0053120255,
        "twoHundredDayAverageChangePercent": -0.003975849,
        "sourceInterval": 15,
        "exchangeDataDelayedBy": 0,
        "cryptoTradeable": false,
        "hasPrePostMarketData": false,
        "firstTradeDateMilliseconds": 1070236800000,
        "regularMarketDayRange": "1.340285 - 1.3476363",
        "fullExchangeName": "CCY",
        "averageDailyVolume3Month": 0,
        "fiftyTwoWeekLowChange": 0.017920017,
        "fiftyTwoWeekLowChangePercent": 0.014808385,
        "fiftyTwoWeekRange": "1.2101264 - 1.378873",
        "fiftyTwoWeekHighChange": -0.08320999,
        "fiftyTwoWeekHighChangePercent": -0.06034638,
        "fiftyTwoWeekChangePercent": -7.340288,
        "fiftyDayAverageChange": -0.010706723,
        "fiftyDayAverageChangePercent": -0.008071335,
        "trailingPegRatio": null
    },
    {
        "maxAge": 86400,
        "priceHint": 4,
        "previousClose": 0.66979235,
        "open": 0.66979235,
        "dayLow": 0.6663557,
        "dayHigh": 0.6702413,
        "regularMarketPreviousClose": 0.66979235,
        "regularMarketOpen": 0.66979235,
        "regularMarketDayLow": 0.6663557,
        "regularMarketDayHigh": 0.6702413,
        "volume": 0,
        "regularMarketVolume": 0,
        "averageVolume": 0,
        "averageVolume10days": 0,
        "averageDailyVolume10Day": 0,
        "bid": 0.66737854,
        "ask": 0.6669334,
        "bidSize": 0,
        "askSize": 0,
        "fiftyTwoWeekLow": 0.5923083,
        "fiftyTwoWeekHigh": 0.6728117,
        "allTimeHigh": 1.811594,
        "allTimeLow": 0.21762,
        "fiftyDayAverage": 0.65653586,
        "twoHundredDayAverage": 0.6495918,
        "currency": "USD",
        "tradeable": false,
        "quoteType": "CURRENCY",
        "symbol": "AUDUSD=X",
        "language": "en-US",
        "region": "US",
        "typeDisp": "Currency",
        "quoteSourceName": "Delayed Quote",
        "triggerable": true,
        "customPriceAlertConfidence": "HIGH",
        "shortName": "AUD/USD",
        "longName": "AUD/USD",
        "regularMarketChangePercent": -0.3603806,
        "regularMarketPrice": 0.66737854,
        "regularMarketChange": -0.0024138093,
        "marketState": "REGULAR",
        "corporateActions": [],
        "regularMarketTime": 1767197817,
        "exchange": "CCY",
        "messageBoardId": "finmb_AUD_X",
        "exchangeTimezoneName": "Europe/London",
        "exchangeTimezoneShortName": "GMT",
        "gmtOffSetMilliseconds": 0,
        "market": "ccy_market",
        "esgPopulated": false,
        "sourceInterval": 15,
        "exchangeDataDelayedBy": 0,
        "cryptoTradeable": false,
        "hasPrePostMarketData": false,
        "firstTradeDateMilliseconds": 1147734000000,
        "regularMarketDayRange": "0.6663557 - 0.6702413",
        "fullExchangeName": "CCY",
        "averageDailyVolume3Month": 0,
        "fiftyTwoWeekLowChange": 0.012099981,
        "fiftyTwoWeekLowChangePercent": 0.02042852,
        "fiftyTwoWeekRange": "0.5923083 - 0.6728117",
        "fiftyTwoWeekHighChange": -0.18991005,
        "fiftyTwoWeekHighChangePercent": -0.2822633,
        "fiftyTwoWeekChangePercent": -7.4871182,
        "fiftyDayAverageChange": -0.02474606,
        "fiftyDayAverageChangePercent": -0.037691865,
        "twoHundredDayAverageChange": -0.04102838,
        "twoHundredDayAverageChangePercent": -0.06316025,
        "trailingPegRatio": null
    },
    {
        "maxAge": 86400,
        "priceHint": 4,
        "previousClose": 0.5792736,
        "open": 0.5791729,
        "dayLow": 0.5742836,
        "dayHigh": 0.5793743,
        "regularMarketPreviousClose": 0.5792736,
        "regularMarketOpen": 0.5791729,
        "regularMarketDayLow": 0.5742836,
        "regularMarketDayHigh": 0.5793743,
        "volume": 0,
        "regularMarketVolume": 0,
        "averageVolume": 0,
        "averageVolume10days": 0,
        "averageDailyVolume10Day": 0,
        "bid": 0.57550645,
        "ask": 0.5751754,
        "bidSize": 0,
        "askSize": 0,
        "fiftyTwoWeekLow": 0.5490704,
        "fiftyTwoWeekHigh": 0.6121187,
        "allTimeHigh": 2.0371,
        "allTimeLow": 0.8187,
        "fiftyDayAverage": 0.5727221,
        "twoHundredDayAverage": 0.58586556,
        "currency": "USD",
        "tradeable": false,
        "quoteType": "CURRENCY",
        "symbol": "NZDUSD=X",
        "language": "en-US",
        "region": "US",
        "typeDisp": "Currency",
        "quoteSourceName": "Delayed Quote",
        "triggerable": true,
        "customPriceAlertConfidence": "HIGH",
        "shortName": "NZD/USD",
        "longName": "NZD/USD",
        "regularMarketChangePercent": -0.6503204,
        "regularMarketPrice": 0.57550645,
        "regularMarketChange": -0.0037671328,
        "marketState": "REGULAR",
        "corporateActions": [],
        "regularMarketTime": 1767197817,
        "exchange": "CCY",
        "messageBoardId": "finmb_NZD_X",
        "exchangeTimezoneName": "Europe/London",
        "exchangeTimezoneShortName": "GMT",
        "gmtOffSetMilliseconds": 0,
        "market": "ccy_market",
        "esgPopulated": false,
        "sourceInterval": 15,
        "exchangeDataDelayedBy": 0,
        "cryptoTradeable": false,
        "hasPrePostMarketData": false,
        "firstTradeDateMilliseconds": 1070236800000,
        "regularMarketDayRange": "0.5742836 - 0.5793743",
        "fullExchangeName": "CCY",
        "averageDailyVolume3Month": 0,
        "fiftyTwoWeekLowChange": 0.10393,
        "fiftyTwoWeekLowChangePercent": 0.18928355,
        "fiftyTwoWeekRange": "0.5490704 - 0.6121187",
        "fiftyTwoWeekHighChange": -0.08366001,
        "fiftyTwoWeekHighChangePercent": -0.13667284,
        "fiftyTwoWeekChangePercent": -3.6201596,
        "fiftyDayAverageChange": -0.008447647,
        "fiftyDayAverageChangePercent": -0.014749994,
        "twoHundredDayAverageChange": 0.030723691,
        "twoHundredDayAverageChangePercent": 0.052441537,
        "trailingPegRatio": null
    },
    {
        "maxAge": 86400,
        "priceHint": 4,
        "previousClose": 183.646,
        "open": 183.648,
        "dayLow": 183.53,
        "dayHigh": 184.244,
        "regularMarketPreviousClose": 183.646,
        "regularMarketOpen": 183.648,
        "regularMarketDayLow": 183.53,
        "regularMarketDayHigh": 184.244,
        "volume": 0,
        "regularMarketVolume": 0,
        "averageVolume": 0,
        "averageVolume10days": 0,
        "averageDailyVolume10Day": 0,
        "bid": 184.107,
        "ask": 184.118,
        "bidSize": 0,
        "askSize": 0,
        "fiftyTwoWeekLow": 154.813,
        "fiftyTwoWeekHigh": 184.903,
        "allTimeHigh": 184.903,
        "allTimeLow": 94.134,
        "fiftyDayAverage": 180.19707,
        "twoHundredDayAverage": 171.46599,
        "currency": "JPY",
        "tradeable": false,
        "quoteType": "CURRENCY",
        "symbol": "EURJPY=X",
        "language": "en-US",
        "region": "US",
        "typeDisp": "Currency",
        "quoteSourceName": "Delayed Quote",
        "triggerable": true,
        "customPriceAlertConfidence": "HIGH",
        "regularMarketChangePercent": 0.24612507,
        "regularMarketPrice": 184.098,
        "exchange": "CCY",
        "messageBoardId": "finmb_EURJPY_X",
        "exchangeTimezoneName": "Europe/London",
        "exchangeTimezoneShortName": "GMT",
        "gmtOffSetMilliseconds": 0,
        "market": "ccy_market",
        "esgPopulated": false,
        "corporateActions": [],
        "regularMarketTime": 1767197916,
        "marketState": "REGULAR",
        "twoHundredDayAverageChange": 12.632019,
        "twoHundredDayAverageChangePercent": 0.0736707,
        "sourceInterval": 15,
        "exchangeDataDelayedBy": 0,
        "cryptoTradeable": false,
        "shortName": "EUR/JPY",
        "longName": "EUR/JPY",
        "hasPrePostMarketData": false,
        "firstTradeDateMilliseconds": 1043280000000,
        "regularMarketChange": 0.4520111,
        "regularMarketDayRange": "183.53 - 184.244",
        "fullExchangeName": "CCY",
        "averageDailyVolume3Month": 0,
        "fiftyTwoWeekLowChange": 29.285004,
        "fiftyTwoWeekLowChangePercent": 0.18916371,
        "fiftyTwoWeekRange": "154.813 - 184.903",
        "fiftyTwoWeekHighChange": -0.8049927,
        "fiftyTwoWeekHighChangePercent": -0.0043535945,
        "fiftyTwoWeekChangePercent": 12.516535,
        "fiftyDayAverageChange": 3.90094,
        "fiftyDayAverageChangePercent": 0.021648187,
        "trailingPegRatio": null
    },
    {
        "maxAge": 86400,
        "priceHint": 4,
        "previousClose": 210.515,
        "open": 210.556,
        "dayLow": 210.251,
        "dayHigh": 211.095,
        "regularMarketPreviousClose": 210.515,
        "regularMarketOpen": 210.556,
        "regularMarketDayLow": 210.251,
        "regularMarketDayHigh": 211.095,
        "volume": 0,
        "regularMarketVolume": 0,
        "averageVolume": 0,
        "averageVolume10days": 0,
        "averageDailyVolume10Day": 0,
        "bid": 210.904,
        "ask": 210.915,
        "bidSize": 0,
        "askSize": 0,
        "fiftyTwoWeekLow": 184.417,
        "fiftyTwoWeekHigh": 211.581,
        "allTimeHigh": 251.076,
        "allTimeLow": 116.95,
        "fiftyDayAverage": 205.52882,
        "twoHundredDayAverage": 198.7159,
        "currency": "JPY",
        "tradeable": false,
        "quoteType": "CURRENCY",
        "symbol": "GBPJPY=X",
        "language": "en-US",
        "region": "US",
        "typeDisp": "Currency",
        "quoteSourceName": "Delayed Quote",
        "triggerable": true,
        "customPriceAlertConfidence": "HIGH",
        "shortName": "GBP/JPY",
        "longName": "GBP/JPY",
        "marketState": "REGULAR",
        "fullExchangeName": "CCY",
        "averageDailyVolume3Month": 0,
        "fiftyTwoWeekLowChange": 26.493988,
        "fiftyTwoWeekLowChangePercent": 0.14366348,
        "fiftyTwoWeekRange": "184.417 - 211.581",
        "fiftyTwoWeekHighChange": -0.66999817,
        "fiftyTwoWeekHighChangePercent": -0.0031666274,
        "fiftyTwoWeekChangePercent": 6.762743,
        "corporateActions": [],
        "regularMarketTime": 1767197917,
        "exchange": "CCY",
        "messageBoardId": "finmb_GBPJPY_X",
        "exchangeTimezoneName": "Europe/London",
        "exchangeTimezoneShortName": "GMT",
        "gmtOffSetMilliseconds": 0,
        "market": "ccy_market",
        "esgPopulated": false,
        "regularMarketChangePercent": 0.18810646,
        "fiftyDayAverageChange": 5.3821716,
        "fiftyDayAverageChangePercent": 0.026186943,
        "twoHundredDayAverageChange": 12.195099,
        "twoHundredDayAverageChangePercent": 0.06136952,
        "sourceInterval": 15,
        "exchangeDataDelayedBy": 0,
        "cryptoTradeable": false,
        "regularMarketPrice": 210.911,
        "hasPrePostMarketData": false,
        "firstTradeDateMilliseconds": 1070236800000,
        "regularMarketChange": 0.3959961,
        "regularMarketDayRange": "210.251 - 211.095",
        "trailingPegRatio": null
    },
    {
        "maxAge": 86400,
        "priceHint": 4,
        "previousClose": 0.87204,
        "open": 0.87203,
        "dayLow": 0.87169,
        "dayHigh": 0.8746,
        "regularMarketPreviousClose": 0.87204,
        "regularMarketOpen": 0.87203,
        "regularMarketDayLow": 0.87169,
        "regularMarketDayHigh": 0.8746,
        "volume": 0,
        "regularMarketVolume": 0,
        "averageVolume": 0,
        "averageVolume10days": 0,
        "averageDailyVolume10Day": 0,
        "bid": 0.87285,
        "ask": 0.87294,
        "bidSize": 0,
        "askSize": 0,
        "fiftyTwoWeekLow": 0.82348,
        "fiftyTwoWeekHigh": 0.88653,
        "allTimeHigh": 0.9797,
        "allTimeLow": 0.0066,
        "fiftyDayAverage": 0.8766896,
        "twoHundredDayAverage": 0.8625679,
        "currency": "GBP",
        "tradeable": false,
        "quoteType": "CURRENCY",
        "symbol": "EURGBP=X",
        "language": "en-US",
        "region": "US",
        "typeDisp": "Currency",
        "quoteSourceName": "Delayed Quote",
        "triggerable": true,
        "customPriceAlertConfidence": "HIGH",
        "shortName": "EUR/GBP",
        "longName": "EUR/GBP",
        "corporateActions": [],
        "regularMarketTime": 1767197918,
        "exchange": "CCY",
        "messageBoardId": "finmb_EURGBP_X",
        "exchangeTimezoneName": "Europe/London",
        "exchangeTimezoneShortName": "GMT",
        "gmtOffSetMilliseconds": 0,
        "market": "ccy_market",
        "esgPopulated": false,
        "regularMarketChangePercent": 0.08486438,
        "regularMarketPrice": 0.87278,
        "fiftyTwoWeekLowChange": 0.049300015,
        "fiftyTwoWeekLowChangePercent": 0.059867896,
        "fiftyTwoWeekRange": "0.82348 - 0.88653",
        "fiftyTwoWeekHighChange": -0.013749957,
        "fiftyTwoWeekHighChangePercent": -0.0155098615,
        "fiftyTwoWeekChangePercent": 5.3904653,
        "fiftyDayAverageChange": -0.003909588,
        "fiftyDayAverageChangePercent": -0.004459489,
        "twoHundredDayAverageChange": 0.010212123,
        "twoHundredDayAverageChangePercent": 0.011839211,
        "sourceInterval": 15,
        "exchangeDataDelayedBy": 0,
        "cryptoTradeable": false,
        "marketState": "REGULAR",
        "hasPrePostMarketData": false,
        "firstTradeDateMilliseconds": 915408000000,
        "regularMarketChange": 0.00074005127,
        "regularMarketDayRange": "0.87169 - 0.8746",
        "fullExchangeName": "CCY",
        "averageDailyVolume3Month": 0,
        "trailingPegRatio": null
    },
    {
        "maxAge": 86400,
        "priceHint": 4,
        "previousClose": 1.6081,
        "open": 1.60808,
        "dayLow": 1.60591,
        "dayHigh": 1.61097,
        "regularMarketPreviousClose": 1.6081,
        "regularMarketOpen": 1.60808,
        "regularMarketDayLow": 1.60591,
        "regularMarketDayHigh": 1.61097,
        "volume": 0,
        "regularMarketVolume": 0,
        "averageVolume": 0,
        "averageVolume10days": 0,
        "averageDailyVolume10Day": 0,
        "bid": 1.61049,
        "ask": 1.61069,
        "bidSize": 0,
        "askSize": 0,
        "fiftyTwoWeekLow": 1.46876,
        "fiftyTwoWeekHigh": 1.64657,
        "allTimeHigh": 1.7498,
        "allTimeLow": 1.2126,
        "fiftyDayAverage": 1.6210092,
        "twoHundredDayAverage": 1.5985173,
        "currency": "CAD",
        "tradeable": false,
        "quoteType": "CURRENCY",
        "symbol": "EURCAD=X",
        "language": "en-US",
        "region": "US",
        "typeDisp": "Currency",
        "quoteSourceName": "Delayed Quote",
        "triggerable": true,
        "customPriceAlertConfidence": "HIGH",
        "shortName": "EUR/CAD",
        "longName": "EUR/CAD",
        "marketState": "REGULAR",
        "fullExchangeName": "CCY",
        "averageDailyVolume3Month": 0,
        "fiftyTwoWeekLowChange": 0.14166999,
        "fiftyTwoWeekLowChangePercent": 0.09645551,
        "fiftyTwoWeekRange": "1.46876 - 1.64657",
        "fiftyTwoWeekHighChange": -0.036139965,
        "fiftyTwoWeekHighChangePercent": -0.021948636,
        "fiftyTwoWeekChangePercent": 8.28594,
        "corporateActions": [],
        "regularMarketTime": 1767197918,
        "exchange": "CCY",
        "messageBoardId": "finmb_EURCAD_X",
        "exchangeTimezoneName": "Europe/London",
        "exchangeTimezoneShortName": "GMT",
        "gmtOffSetMilliseconds": 0,
        "market": "ccy_market",
        "esgPopulated": false,
        "regularMarketChangePercent": 0.1448881,
        "fiftyDayAverageChange": -0.010579228,
        "fiftyDayAverageChangePercent": -0.006526322,
        "twoHundredDayAverageChange": 0.0119127035,
        "twoHundredDayAverageChangePercent": 0.007452346,
        "sourceInterval": 15,
        "exchangeDataDelayedBy": 0,
        "cryptoTradeable": false,
        "regularMarketPrice": 1.61043,
        "hasPrePostMarketData": false,
        "firstTradeDateMilliseconds": 1070236800000,
        "regularMarketChange": 0.0023299456,
        "regularMarketDayRange": "1.60591 - 1.61097",
        "trailingPegRatio": null
    },
    {
        "maxAge": 86400,
        "priceHint": 4,
        "previousClose": 10.80329,
        "open": 10.79889,
        "dayLow": 10.79475,
        "dayHigh": 10.8342,
        "regularMarketPreviousClose": 10.80329,
        "regularMarketOpen": 10.79889,
        "regularMarketDayLow": 10.79475,
        "regularMarketDayHigh": 10.8342,
        "volume": 0,
        "regularMarketVolume": 0,
        "averageVolume": 0,
        "averageVolume10days": 0,
        "averageDailyVolume10Day": 0,
        "bid": 10.81445,
        "ask": 10.81842,
        "bidSize": 0,
        "askSize": 0,
        "fiftyTwoWeekLow": 10.66621,
        "fiftyTwoWeekHigh": 11.5335,
        "allTimeHigh": 20.8097,
        "allTimeLow": 8.0333,
        "fiftyDayAverage": 10.93192,
        "twoHundredDayAverage": 11.00192,
        "currency": "SEK",
        "tradeable": false,
        "quoteType": "CURRENCY",
        "symbol": "EURSEK=X",
        "language": "en-US",
        "region": "US",
        "typeDisp": "Currency",
        "quoteSourceName": "Delayed Quote",
        "triggerable": true,
        "customPriceAlertConfidence": "HIGH",
        "shortName": "EUR/SEK",
        "longName": "EUR/SEK",
        "marketState": "REGULAR",
        "fullExchangeName": "CCY",
        "averageDailyVolume3Month": 0,
        "fiftyTwoWeekLowChange": 0.14847946,
        "fiftyTwoWeekLowChangePercent": 0.013920546,
        "fiftyTwoWeekRange": "10.66621 - 11.5335",
        "fiftyTwoWeekHighChange": -0.7188101,
        "fiftyTwoWeekHighChangePercent": -0.062323675,
        "fiftyTwoWeekChangePercent": -5.6357145,
        "corporateActions": [],
        "regularMarketTime": 1767197918,
        "exchange": "CCY",
        "messageBoardId": "finmb_EURSEK_X",
        "exchangeTimezoneName": "Europe/London",
        "exchangeTimezoneShortName": "GMT",
        "gmtOffSetMilliseconds": 0,
        "market": "ccy_market",
        "esgPopulated": false,
        "regularMarketChangePercent": 0.10552309,
        "fiftyDayAverageChange": -0.117230415,
        "fiftyDayAverageChangePercent": -0.01072368,
        "twoHundredDayAverageChange": -0.18723011,
        "twoHundredDayAverageChangePercent": -0.01701795,
        "sourceInterval": 15,
        "exchangeDataDelayedBy": 0,
        "cryptoTradeable": false,
        "regularMarketPrice": 10.81469,
        "hasPrePostMarketData": false,
        "firstTradeDateMilliseconds": 911347200000,
        "regularMarketChange": 0.011399269,
        "regularMarketDayRange": "10.79475 - 10.8342",
        "trailingPegRatio": null
    },
    {
        "maxAge": 86400,
        "priceHint": 4,
        "previousClose": 0.93001,
        "open": 0.93004,
        "dayLow": 0.92926,
        "dayHigh": 0.9317,
        "regularMarketPreviousClose": 0.93001,
        "regularMarketOpen": 0.93004,
        "regularMarketDayLow": 0.92926,
        "regularMarketDayHigh": 0.9317,
        "volume": 0,
        "regularMarketVolume": 0,
        "averageVolume": 0,
        "averageVolume10days": 0,
        "averageDailyVolume10Day": 0,
        "bid": 0.93096,
        "ask": 0.93114,
        "bidSize": 0,
        "askSize": 0,
        "fiftyTwoWeekLow": 0.91798,
        "fiftyTwoWeekHigh": 0.9661,
        "allTimeHigh": 1.6825,
        "allTimeLow": 0.8643,
        "fiftyDayAverage": 0.9300526,
        "twoHundredDayAverage": 0.9347589,
        "currency": "CHF",
        "tradeable": false,
        "quoteType": "CURRENCY",
        "symbol": "EURCHF=X",
        "language": "en-US",
        "region": "US",
        "typeDisp": "Currency",
        "quoteSourceName": "Delayed Quote",
        "triggerable": true,
        "customPriceAlertConfidence": "HIGH",
        "shortName": "EUR/CHF",
        "longName": "EUR/CHF",
        "marketState": "REGULAR",
        "fullExchangeName": "CCY",
        "averageDailyVolume3Month": 0,
        "fiftyTwoWeekLowChange": 0.013000011,
        "fiftyTwoWeekLowChangePercent": 0.014161541,
        "fiftyTwoWeekRange": "0.91798 - 0.9661",
        "fiftyTwoWeekHighChange": -0.03511995,
        "fiftyTwoWeekHighChangePercent": -0.036352295,
        "fiftyTwoWeekChangePercent": -1.1568248,
        "corporateActions": [],
        "regularMarketTime": 1767197919,
        "exchange": "CCY",
        "messageBoardId": "finmb_EURCHF_X",
        "exchangeTimezoneName": "Europe/London",
        "exchangeTimezoneShortName": "GMT",
        "gmtOffSetMilliseconds": 0,
        "market": "ccy_market",
        "esgPopulated": false,
        "regularMarketChangePercent": 0.10430509,
        "fiftyDayAverageChange": 0.0009274483,
        "fiftyDayAverageChangePercent": 0.0009971998,
        "twoHundredDayAverageChange": -0.0037788749,
        "twoHundredDayAverageChangePercent": -0.00404262,
        "sourceInterval": 15,
        "exchangeDataDelayedBy": 0,
        "cryptoTradeable": false,
        "regularMarketPrice": 0.93098,
        "hasPrePostMarketData": false,
        "firstTradeDateMilliseconds": 1043280000000,
        "regularMarketChange": 0.000970006,
        "regularMarketDayRange": "0.92926 - 0.9317",
        "trailingPegRatio": null
    },
    {
        "maxAge": 86400,
        "priceHint": 4,
        "previousClose": 385.52,
        "open": 385.84,
        "dayLow": 383.55,
        "dayHigh": 386.28,
        "regularMarketPreviousClose": 385.52,
        "regularMarketOpen": 385.84,
        "regularMarketDayLow": 383.55,
        "regularMarketDayHigh": 386.28,
        "volume": 0,
        "regularMarketVolume": 0,
        "averageVolume": 0,
        "averageVolume10days": 0,
        "averageDailyVolume10Day": 0,
        "bid": 383.931,
        "ask": 384.347,
        "bidSize": 0,
        "askSize": 0,
        "fiftyTwoWeekLow": 380.029,
        "fiftyTwoWeekHigh": 416.301,
        "allTimeHigh": 433.812,
        "allTimeLow": 227.75,
        "fiftyDayAverage": 384.98096,
        "twoHundredDayAverage": 395.14197,
        "currency": "HUF",
        "tradeable": false,
        "quoteType": "CURRENCY",
        "symbol": "EURHUF=X",
        "language": "en-US",
        "region": "US",
        "typeDisp": "Currency",
        "quoteSourceName": "Delayed Quote",
        "triggerable": true,
        "customPriceAlertConfidence": "HIGH",
        "corporateActions": [],
        "regularMarketTime": 1767197920,
        "exchange": "CCY",
        "messageBoardId": "finmb_EURHUF_X",
        "exchangeTimezoneName": "Europe/London",
        "exchangeTimezoneShortName": "GMT",
        "gmtOffSetMilliseconds": 0,
        "market": "ccy_market",
        "esgPopulated": false,
        "regularMarketChangePercent": -0.41476423,
        "regularMarketPrice": 383.921,
        "regularMarketChange": -1.598999,
        "regularMarketDayRange": "383.55 - 386.28",
        "fullExchangeName": "CCY",
        "averageDailyVolume3Month": 0,
        "fiftyTwoWeekLowChange": 3.8919983,
        "fiftyTwoWeekLowChangePercent": 0.010241319,
        "fiftyTwoWeekRange": "380.029 - 416.301",
        "fiftyTwoWeekHighChange": -32.380005,
        "fiftyTwoWeekHighChangePercent": -0.07778027,
        "fiftyTwoWeekChangePercent": -5.925894,
        "fiftyDayAverageChange": -1.059967,
        "fiftyDayAverageChangePercent": -0.0027532973,
        "twoHundredDayAverageChange": -11.220978,
        "twoHundredDayAverageChangePercent": -0.028397333,
        "sourceInterval": 15,
        "exchangeDataDelayedBy": 0,
        "cryptoTradeable": false,
        "hasPrePostMarketData": false,
        "firstTradeDateMilliseconds": 1070236800000,
        "marketState": "REGULAR",
        "shortName": "EUR/HUF",
        "longName": "EUR/HUF",
        "trailingPegRatio": null
    },
    {
        "maxAge": 86400,
        "priceHint": 4,
        "previousClose": 6.9956,
        "open": 6.9921,
        "dayLow": 6.986,
        "dayHigh": 7.0012,
        "regularMarketPreviousClose": 6.9956,
        "regularMarketOpen": 6.9921,
        "regularMarketDayLow": 6.986,
        "regularMarketDayHigh": 7.0012,
        "volume": 0,
        "regularMarketVolume": 0,
        "averageVolume": 0,
        "averageVolume10days": 0,
        "averageDailyVolume10Day": 0,
        "bid": 6.9926,
        "ask": 6.9936,
        "bidSize": 0,
        "askSize": 0,
        "fiftyTwoWeekLow": 6.986,
        "fiftyTwoWeekHigh": 7.35,
        "allTimeHigh": 8.3169,
        "allTimeLow": 2.2015,
        "fiftyDayAverage": 7.086644,
        "twoHundredDayAverage": 7.1642313,
        "currency": "CNY",
        "tradeable": false,
        "quoteType": "CURRENCY",
        "symbol": "CNY=X",
        "language": "en-US",
        "region": "US",
        "typeDisp": "Currency",
        "quoteSourceName": "Delayed Quote",
        "triggerable": true,
        "customPriceAlertConfidence": "HIGH",
        "shortName": "USD/CNY",
        "longName": "USD/CNY",
        "regularMarketChangePercent": -0.042887807,
        "regularMarketPrice": 6.9926,
        "regularMarketChange": -0.0030002594,
        "marketState": "REGULAR",
        "fullExchangeName": "CCY",
        "averageDailyVolume3Month": 0,
        "fiftyTwoWeekLowChange": 0.006599903,
        "fiftyTwoWeekLowChangePercent": 0.00094473275,
        "fiftyTwoWeekRange": "6.986 - 7.35",
        "fiftyTwoWeekHighChange": -0.35739994,
        "fiftyTwoWeekHighChangePercent": -0.04862584,
        "fiftyTwoWeekChangePercent": -4.0078936,
        "corporateActions": [],
        "regularMarketTime": 1767196792,
        "exchange": "CCY",
        "messageBoardId": "finmb_CNY_X",
        "exchangeTimezoneName": "Europe/London",
        "exchangeTimezoneShortName": "GMT",
        "gmtOffSetMilliseconds": 0,
        "market": "ccy_market",
        "esgPopulated": false,
        "fiftyDayAverageChange": -0.09404421,
        "fiftyDayAverageChangePercent": -0.013270627,
        "twoHundredDayAverageChange": -0.17163134,
        "twoHundredDayAverageChangePercent": -0.0239567,
        "sourceInterval": 15,
        "exchangeDataDelayedBy": 0,
        "cryptoTradeable": false,
        "hasPrePostMarketData": false,
        "firstTradeDateMilliseconds": 993423600000,
        "regularMarketDayRange": "6.986 - 7.0012",
        "trailingPegRatio": null
    },
    {
        "maxAge": 86400,
        "priceHint": 4,
        "previousClose": 7.7806,
        "open": 7.7804,
        "dayLow": 7.77999,
        "dayHigh": 7.7849,
        "regularMarketPreviousClose": 7.7806,
        "regularMarketOpen": 7.7804,
        "regularMarketDayLow": 7.77999,
        "regularMarketDayHigh": 7.7849,
        "volume": 0,
        "regularMarketVolume": 0,
        "averageVolume": 0,
        "averageVolume10days": 0,
        "averageDailyVolume10Day": 0,
        "bid": 7.783,
        "ask": 7.784,
        "bidSize": 0,
        "askSize": 0,
        "fiftyTwoWeekLow": 7.749,
        "fiftyTwoWeekHigh": 7.85004,
        "allTimeHigh": 7.8627,
        "allTimeLow": 7.6431,
        "fiftyDayAverage": 7.7769065,
        "twoHundredDayAverage": 7.8003683,
        "currency": "HKD",
        "tradeable": false,
        "quoteType": "CURRENCY",
        "symbol": "HKD=X",
        "language": "en-US",
        "region": "US",
        "typeDisp": "Currency",
        "quoteSourceName": "Delayed Quote",
        "triggerable": true,
        "customPriceAlertConfidence": "HIGH",
        "shortName": "USD/HKD",
        "regularMarketChangePercent": 0.02891315,
        "regularMarketPrice": 7.78285,
        "longName": "USD/HKD",
        "regularMarketChange": 0.0022497177,
        "marketState": "REGULAR",
        "corporateActions": [],
        "regularMarketTime": 1767197920,
        "exchange": "CCY",
        "messageBoardId": "finmb_HKD_X",
        "exchangeTimezoneName": "Europe/London",
        "exchangeTimezoneShortName": "GMT",
        "gmtOffSetMilliseconds": 0,
        "market": "ccy_market",
        "esgPopulated": false,
        "hasPrePostMarketData": false,
        "firstTradeDateMilliseconds": 995238000000,
        "regularMarketDayRange": "7.77999 - 7.7849",
        "fullExchangeName": "CCY",
        "averageDailyVolume3Month": 0,
        "fiftyTwoWeekLowChange": 0.033849716,
        "fiftyTwoWeekLowChangePercent": 0.004368269,
        "fiftyTwoWeekRange": "7.749 - 7.85004",
        "fiftyTwoWeekHighChange": -0.06719017,
        "fiftyTwoWeekHighChangePercent": -0.008559214,
        "fiftyTwoWeekChangePercent": 0.06566048,
        "fiftyDayAverageChange": 0.0059432983,
        "fiftyDayAverageChangePercent": 0.000764224,
        "twoHundredDayAverageChange": -0.01751852,
        "twoHundredDayAverageChangePercent": -0.002245858,
        "sourceInterval": 15,
        "exchangeDataDelayedBy": 0,
        "cryptoTradeable": false,
        "trailingPegRatio": null
    },
    {
        "maxAge": 86400,
        "priceHint": 4,
        "previousClose": 1.28382,
        "open": 1.28381,
        "dayLow": 1.28325,
        "dayHigh": 1.2868,
        "regularMarketPreviousClose": 1.28382,
        "regularMarketOpen": 1.28381,
        "regularMarketDayLow": 1.28325,
        "regularMarketDayHigh": 1.2868,
        "volume": 0,
        "regularMarketVolume": 0,
        "averageVolume": 0,
        "averageVolume10days": 0,
        "averageDailyVolume10Day": 0,
        "bid": 1.2859,
        "ask": 1.28609,
        "bidSize": 0,
        "askSize": 0,
        "fiftyTwoWeekLow": 1.26981,
        "fiftyTwoWeekHigh": 1.37492,
        "allTimeHigh": 1.73,
        "allTimeLow": 1.199,
        "fiftyDayAverage": 1.297026,
        "twoHundredDayAverage": 1.2950962,
        "currency": "SGD",
        "tradeable": false,
        "quoteType": "CURRENCY",
        "symbol": "SGD=X",
        "language": "en-US",
        "region": "US",
        "typeDisp": "Currency",
        "quoteSourceName": "Delayed Quote",
        "triggerable": true,
        "customPriceAlertConfidence": "HIGH",
        "shortName": "USD/SGD",
        "longName": "USD/SGD",
        "regularMarketChangePercent": 0.16123366,
        "regularMarketPrice": 1.28589,
        "regularMarketChange": 0.00206995,
        "marketState": "REGULAR",
        "fiftyDayAverageChange": -0.011136055,
        "fiftyDayAverageChangePercent": -0.008585838,
        "twoHundredDayAverageChange": -0.009206176,
        "twoHundredDayAverageChangePercent": -0.007108488,
        "sourceInterval": 15,
        "exchangeDataDelayedBy": 0,
        "cryptoTradeable": false,
        "corporateActions": [],
        "regularMarketTime": 1767197922,
        "exchange": "CCY",
        "messageBoardId": "finmb_SGD_X",
        "exchangeTimezoneName": "Europe/London",
        "exchangeTimezoneShortName": "GMT",
        "gmtOffSetMilliseconds": 0,
        "market": "ccy_market",
        "esgPopulated": false,
        "hasPrePostMarketData": false,
        "firstTradeDateMilliseconds": 1070236800000,
        "regularMarketDayRange": "1.28325 - 1.2868",
        "fullExchangeName": "CCY",
        "averageDailyVolume3Month": 0,
        "fiftyTwoWeekLowChange": 0.016080022,
        "fiftyTwoWeekLowChangePercent": 0.012663329,
        "fiftyTwoWeekRange": "1.26981 - 1.37492",
        "fiftyTwoWeekHighChange": -0.08903003,
        "fiftyTwoWeekHighChangePercent": -0.06475288,
        "fiftyTwoWeekChangePercent": -5.8998404,
        "trailingPegRatio": null
    },
    {
        "maxAge": 86400,
        "priceHint": 4,
        "previousClose": 89.739,
        "open": 89.729,
        "dayLow": 89.701,
        "dayHigh": 89.95,
        "regularMarketPreviousClose": 89.739,
        "regularMarketOpen": 89.729,
        "regularMarketDayLow": 89.701,
        "regularMarketDayHigh": 89.95,
        "volume": 0,
        "regularMarketVolume": 0,
        "averageVolume": 0,
        "averageVolume10days": 0,
        "averageDailyVolume10Day": 0,
        "bid": 89.822,
        "ask": 89.872,
        "bidSize": 0,
        "askSize": 0,
        "fiftyTwoWeekLow": 72.9671,
        "fiftyTwoWeekHigh": 91.073,
        "allTimeHigh": 91.073,
        "allTimeLow": 38.979,
        "fiftyDayAverage": 89.18562,
        "twoHundredDayAverage": 87.25683,
        "currency": "INR",
        "tradeable": false,
        "quoteType": "CURRENCY",
        "symbol": "INR=X",
        "language": "en-US",
        "region": "US",
        "typeDisp": "Currency",
        "quoteSourceName": "Delayed Quote",
        "triggerable": true,
        "customPriceAlertConfidence": "HIGH",
        "longName": "USD/INR",
        "shortName": "USD/INR",
        "regularMarketChange": 0.08300018,
        "regularMarketChangePercent": 0.09248962,
        "regularMarketPrice": 89.822,
        "fiftyTwoWeekHighChange": -1.2509995,
        "corporateActions": [],
        "regularMarketTime": 1767197911,
        "exchange": "CCY",
        "messageBoardId": "finmb_INR_X",
        "exchangeTimezoneName": "Europe/London",
        "exchangeTimezoneShortName": "GMT",
        "gmtOffSetMilliseconds": 0,
        "market": "ccy_market",
        "esgPopulated": false,
        "marketState": "REGULAR",
        "hasPrePostMarketData": false,
        "firstTradeDateMilliseconds": 1070236800000,
        "regularMarketDayRange": "89.701 - 89.95",
        "fullExchangeName": "CCY",
        "averageDailyVolume3Month": 0,
        "fiftyTwoWeekLowChange": 16.854897,
        "fiftyTwoWeekLowChangePercent": 0.23099309,
        "fiftyTwoWeekRange": "72.9671 - 91.073",
        "fiftyTwoWeekHighChangePercent": -0.0137362275,
        "fiftyTwoWeekChangePercent": 4.796016,
        "fiftyDayAverageChange": 0.6363754,
        "fiftyDayAverageChangePercent": 0.007135404,
        "twoHundredDayAverageChange": 2.5651703,
        "twoHundredDayAverageChangePercent": 0.029397931,
        "sourceInterval": 15,
        "exchangeDataDelayedBy": 0,
        "cryptoTradeable": false,
        "trailingPegRatio": null
    },
    {
        "maxAge": 86400,
        "priceHint": 4,
        "previousClose": 17.98586,
        "open": 17.978,
        "dayLow": 17.947,
        "dayHigh": 18.012,
        "regularMarketPreviousClose": 17.98586,
        "regularMarketOpen": 17.978,
        "regularMarketDayLow": 17.947,
        "regularMarketDayHigh": 18.012,
        "volume": 0,
        "regularMarketVolume": 0,
        "averageVolume": 0,
        "averageVolume10days": 0,
        "averageDailyVolume10Day": 0,
        "bid": 17.9993,
        "ask": 18.0098,
        "bidSize": 0,
        "askSize": 0,
        "fiftyTwoWeekLow": 17.87,
        "fiftyTwoWeekHigh": 21.28773,
        "allTimeHigh": 25.76534,
        "allTimeLow": 9.834,
        "fiftyDayAverage": 18.281572,
        "twoHundredDayAverage": 18.858782,
        "currency": "MXN",
        "tradeable": false,
        "quoteType": "CURRENCY",
        "symbol": "MXN=X",
        "language": "en-US",
        "region": "US",
        "typeDisp": "Currency",
        "quoteSourceName": "Delayed Quote",
        "triggerable": true,
        "customPriceAlertConfidence": "HIGH",
        "regularMarketChangePercent": 0.09918294,
        "regularMarketPrice": 18.0037,
        "shortName": "USD/MXN",
        "longName": "USD/MXN",
        "regularMarketChange": 0.017839432,
        "corporateActions": [],
        "regularMarketTime": 1767197923,
        "cryptoTradeable": false,
        "marketState": "REGULAR",
        "fiftyDayAverageChange": -0.2778721,
        "fiftyDayAverageChangePercent": -0.015199573,
        "twoHundredDayAverageChange": -0.85508156,
        "twoHundredDayAverageChangePercent": -0.045341294,
        "sourceInterval": 15,
        "exchangeDataDelayedBy": 0,
        "hasPrePostMarketData": false,
        "firstTradeDateMilliseconds": 1070236800000,
        "fiftyTwoWeekChangePercent": -13.720822,
        "exchange": "CCY",
        "messageBoardId": "finmb_MXN_X",
        "exchangeTimezoneName": "Europe/London",
        "exchangeTimezoneShortName": "GMT",
        "gmtOffSetMilliseconds": 0,
        "market": "ccy_market",
        "esgPopulated": false,
        "regularMarketDayRange": "17.947 - 18.012",
        "fullExchangeName": "CCY",
        "averageDailyVolume3Month": 0,
        "fiftyTwoWeekLowChange": 0.13369942,
        "fiftyTwoWeekLowChangePercent": 0.00748178,
        "fiftyTwoWeekRange": "17.87 - 21.28773",
        "fiftyTwoWeekHighChange": -3.284029,
        "fiftyTwoWeekHighChangePercent": -0.15426864,
        "trailingPegRatio": null
    },
    {
        "maxAge": 86400,
        "priceHint": 4,
        "previousClose": 58.803,
        "open": 58.814,
        "dayLow": 58.773,
        "dayHigh": 58.951,
        "regularMarketPreviousClose": 58.803,
        "regularMarketOpen": 58.814,
        "regularMarketDayLow": 58.773,
        "regularMarketDayHigh": 58.951,
        "volume": 0,
        "regularMarketVolume": 0,
        "averageVolume": 0,
        "averageVolume10days": 0,
        "averageDailyVolume10Day": 0,
        "bid": 58.818,
        "ask": 58.893,
        "bidSize": 0,
        "askSize": 0,
        "fiftyTwoWeekLow": 50.323,
        "fiftyTwoWeekHigh": 59.496,
        "allTimeHigh": 59.496,
        "allTimeLow": 40.087,
        "fiftyDayAverage": 58.66018,
        "twoHundredDayAverage": 57.203575,
        "currency": "PHP",
        "tradeable": false,
        "quoteType": "CURRENCY",
        "symbol": "PHP=X",
        "language": "en-US",
        "region": "US",
        "typeDisp": "Currency",
        "quoteSourceName": "Delayed Quote",
        "triggerable": true,
        "customPriceAlertConfidence": "HIGH",
        "shortName": "USD/PHP",
        "longName": "USD/PHP",
        "regularMarketChange": 0.01599884,
        "regularMarketChangePercent": 0.027207986,
        "regularMarketPrice": 58.819,
        "fiftyDayAverageChange": 0.1588211,
        "fiftyDayAverageChangePercent": 0.0027074774,
        "twoHundredDayAverageChange": 1.6154251,
        "twoHundredDayAverageChangePercent": 0.028239932,
        "sourceInterval": 15,
        "exchangeDataDelayedBy": 0,
        "cryptoTradeable": false,
        "messageBoardId": "finmb_PHP_X",
        "exchangeTimezoneName": "Europe/London",
        "exchangeTimezoneShortName": "GMT",
        "gmtOffSetMilliseconds": 0,
        "market": "ccy_market",
        "esgPopulated": false,
        "marketState": "REGULAR",
        "hasPrePostMarketData": false,
        "firstTradeDateMilliseconds": 1070236800000,
        "regularMarketDayRange": "58.773 - 58.951",
        "fullExchangeName": "CCY",
        "averageDailyVolume3Month": 0,
        "fiftyTwoWeekLowChange": 8.495998,
        "fiftyTwoWeekLowChangePercent": 0.16882932,
        "fiftyTwoWeekRange": "50.323 - 59.496",
        "fiftyTwoWeekHighChange": -0.67699814,
        "fiftyTwoWeekHighChangePercent": -0.011378885,
        "fiftyTwoWeekChangePercent": 2.8313756,
        "corporateActions": [],
        "regularMarketTime": 1767197918,
        "exchange": "CCY",
        "trailingPegRatio": null
    },
    {
        "maxAge": 86400,
        "priceHint": 4,
        "previousClose": 16778.0,
        "open": 16700.0,
        "dayLow": 16685.0,
        "dayHigh": 16778.0,
        "regularMarketPreviousClose": 16778.0,
        "regularMarketOpen": 16700.0,
        "regularMarketDayLow": 16685.0,
        "regularMarketDayHigh": 16778.0,
        "volume": 0,
        "regularMarketVolume": 0,
        "averageVolume": 0,
        "averageVolume10days": 0,
        "averageDailyVolume10Day": 0,
        "bid": 16715.0,
        "ask": 16722.0,
        "bidSize": 0,
        "askSize": 0,
        "fiftyTwoWeekLow": 14670.4,
        "fiftyTwoWeekHigh": 17322.6,
        "allTimeHigh": 197804.0,
        "allTimeLow": 4.0,
        "fiftyDayAverage": 16639.98,
        "twoHundredDayAverage": 16489.947,
        "currency": "IDR",
        "tradeable": false,
        "quoteType": "CURRENCY",
        "symbol": "IDR=X",
        "language": "en-US",
        "region": "US",
        "typeDisp": "Currency",
        "quoteSourceName": "Delayed Quote",
        "triggerable": true,
        "customPriceAlertConfidence": "HIGH",
        "regularMarketChangePercent": -0.3754917,
        "regularMarketPrice": 16715.0,
        "shortName": "USD/IDR",
        "longName": "USD/IDR",
        "regularMarketChange": -63.0,
        "corporateActions": [],
        "regularMarketTime": 1767193962,
        "cryptoTradeable": false,
        "marketState": "REGULAR",
        "fiftyDayAverageChange": 75.01953,
        "fiftyDayAverageChangePercent": 0.0045083906,
        "twoHundredDayAverageChange": 225.05273,
        "twoHundredDayAverageChangePercent": 0.013647875,
        "sourceInterval": 15,
        "exchangeDataDelayedBy": 0,
        "hasPrePostMarketData": false,
        "firstTradeDateMilliseconds": 993682800000,
        "fiftyTwoWeekChangePercent": 3.3239841,
        "exchange": "CCY",
        "messageBoardId": "finmb_IDR_X",
        "exchangeTimezoneName": "Europe/London",
        "exchangeTimezoneShortName": "GMT",
        "gmtOffSetMilliseconds": 0,
        "market": "ccy_market",
        "esgPopulated": false,
        "regularMarketDayRange": "16685.0 - 16778.0",
        "fullExchangeName": "CCY",
        "averageDailyVolume3Month": 0,
        "fiftyTwoWeekLowChange": 2044.5996,
        "fiftyTwoWeekLowChangePercent": 0.13936904,
        "fiftyTwoWeekRange": "14670.4 - 17322.6",
        "fiftyTwoWeekHighChange": -607.5996,
        "fiftyTwoWeekHighChangePercent": -0.035075545,
        "trailingPegRatio": null
    },
    {
        "maxAge": 86400,
        "priceHint": 4,
        "previousClose": 31.382,
        "open": 31.396,
        "dayLow": 31.38,
        "dayHigh": 31.673,
        "regularMarketPreviousClose": 31.382,
        "regularMarketOpen": 31.396,
        "regularMarketDayLow": 31.38,
        "regularMarketDayHigh": 31.673,
        "volume": 0,
        "regularMarketVolume": 0,
        "averageVolume": 0,
        "averageVolume10days": 0,
        "averageDailyVolume10Day": 0,
        "bid": 31.525,
        "ask": 31.533,
        "bidSize": 0,
        "askSize": 0,
        "fiftyTwoWeekLow": 30.99,
        "fiftyTwoWeekHigh": 34.98,
        "allTimeHigh": 668.8,
        "allTimeLow": 28.011,
        "fiftyDayAverage": 32.0907,
        "twoHundredDayAverage": 32.572056,
        "currency": "THB",
        "tradeable": false,
        "quoteType": "CURRENCY",
        "symbol": "THB=X",
        "language": "en-US",
        "region": "US",
        "typeDisp": "Currency",
        "quoteSourceName": "Delayed Quote",
        "triggerable": true,
        "customPriceAlertConfidence": "HIGH",
        "longName": "USD/THB",
        "shortName": "USD/THB",
        "regularMarketChange": 0.11800003,
        "regularMarketChangePercent": 0.37576038,
        "regularMarketPrice": 31.5,
        "fiftyTwoWeekHighChange": -3.4799995,
        "corporateActions": [],
        "regularMarketTime": 1767197923,
        "exchange": "CCY",
        "messageBoardId": "finmb_THB_X",
        "exchangeTimezoneName": "Europe/London",
        "exchangeTimezoneShortName": "GMT",
        "gmtOffSetMilliseconds": 0,
        "market": "ccy_market",
        "esgPopulated": false,
        "marketState": "REGULAR",
        "hasPrePostMarketData": false,
        "firstTradeDateMilliseconds": 1070236800000,
        "regularMarketDayRange": "31.38 - 31.673",
        "fullExchangeName": "CCY",
        "averageDailyVolume3Month": 0,
        "fiftyTwoWeekLowChange": 0.5100002,
        "fiftyTwoWeekLowChangePercent": 0.01645693,
        "fiftyTwoWeekRange": "30.99 - 34.98",
        "fiftyTwoWeekHighChangePercent": -0.099485405,
        "fiftyTwoWeekChangePercent": -7.728201,
        "fiftyDayAverageChange": -0.59069824,
        "fiftyDayAverageChangePercent": -0.01840715,
        "twoHundredDayAverageChange": -1.0720558,
        "twoHundredDayAverageChangePercent": -0.03291336,
        "sourceInterval": 15,
        "exchangeDataDelayedBy": 0,
        "cryptoTradeable": false,
        "trailingPegRatio": null
    },
    {
        "maxAge": 86400,
        "priceHint": 4,
        "previousClose": 4.045,
        "open": 4.045,
        "dayLow": 4.045,
        "dayHigh": 4.06,
        "regularMarketPreviousClose": 4.045,
        "regularMarketOpen": 4.045,
        "regularMarketDayLow": 4.045,
        "regularMarketDayHigh": 4.06,
        "volume": 0,
        "regularMarketVolume": 0,
        "averageVolume": 0,
        "averageVolume10days": 0,
        "averageDailyVolume10Day": 0,
        "bid": 4.058,
        "ask": 4.0625,
        "bidSize": 0,
        "askSize": 0,
        "fiftyTwoWeekLow": 4.028,
        "fiftyTwoWeekHigh": 4.516,
        "allTimeHigh": 4.978,
        "allTimeLow": 1.6258,
        "fiftyDayAverage": 4.140024,
        "twoHundredDayAverage": 4.235078,
        "currency": "MYR",
        "tradeable": false,
        "quoteType": "CURRENCY",
        "symbol": "MYR=X",
        "language": "en-US",
        "region": "US",
        "typeDisp": "Currency",
        "quoteSourceName": "Delayed Quote",
        "triggerable": true,
        "customPriceAlertConfidence": "HIGH",
        "longName": "USD/MYR",
        "shortName": "USD/MYR",
        "regularMarketChange": 0.013000011,
        "regularMarketChangePercent": 0.3213847,
        "regularMarketPrice": 4.058,
        "fiftyTwoWeekHighChange": -0.4579997,
        "corporateActions": [],
        "regularMarketTime": 1767175298,
        "exchange": "CCY",
        "messageBoardId": "finmb_MYR_X",
        "exchangeTimezoneName": "Europe/London",
        "exchangeTimezoneShortName": "GMT",
        "gmtOffSetMilliseconds": 0,
        "market": "ccy_market",
        "esgPopulated": false,
        "marketState": "REGULAR",
        "hasPrePostMarketData": false,
        "firstTradeDateMilliseconds": 1070236800000,
        "regularMarketDayRange": "4.045 - 4.06",
        "fullExchangeName": "CCY",
        "averageDailyVolume3Month": 0,
        "fiftyTwoWeekLowChange": 0.03000021,
        "fiftyTwoWeekLowChangePercent": 0.0074479175,
        "fiftyTwoWeekRange": "4.028 - 4.516",
        "fiftyTwoWeekHighChangePercent": -0.101417124,
        "fiftyTwoWeekChangePercent": -9.228188,
        "fiftyDayAverageChange": -0.0820241,
        "fiftyDayAverageChangePercent": -0.019812468,
        "twoHundredDayAverageChange": -0.17707777,
        "twoHundredDayAverageChangePercent": -0.041812163,
        "sourceInterval": 15,
        "exchangeDataDelayedBy": 0,
        "cryptoTradeable": false,
        "trailingPegRatio": null
    },
    {
        "maxAge": 86400,
        "priceHint": 4,
        "previousClose": 16.58399,
        "open": 16.5847,
        "dayLow": 16.52,
        "dayHigh": 16.6295,
        "regularMarketPreviousClose": 16.58399,
        "regularMarketOpen": 16.5847,
        "regularMarketDayLow": 16.52,
        "regularMarketDayHigh": 16.6295,
        "volume": 0,
        "regularMarketVolume": 0,
        "averageVolume": 0,
        "averageVolume10days": 0,
        "averageDailyVolume10Day": 0,
        "bid": 16.5593,
        "ask": 16.5693,
        "bidSize": 0,
        "askSize": 0,
        "fiftyTwoWeekLow": 15.4302,
        "fiftyTwoWeekHigh": 19.9285,
        "allTimeHigh": 19.9285,
        "allTimeLow": 1.5715,
        "fiftyDayAverage": 17.076302,
        "twoHundredDayAverage": 17.691635,
        "currency": "ZAR",
        "tradeable": false,
        "quoteType": "CURRENCY",
        "symbol": "ZAR=X",
        "language": "en-US",
        "region": "US",
        "typeDisp": "Currency",
        "quoteSourceName": "Delayed Quote",
        "triggerable": true,
        "customPriceAlertConfidence": "HIGH",
        "longName": "USD/ZAR",
        "shortName": "USD/ZAR",
        "regularMarketChange": -0.025690079,
        "regularMarketChangePercent": -0.15489873,
        "regularMarketPrice": 16.5583,
        "fiftyTwoWeekHighChange": -3.3701992,
        "corporateActions": [],
        "regularMarketTime": 1767197926,
        "exchange": "CCY",
        "messageBoardId": "finmb_ZAR_X",
        "exchangeTimezoneName": "Europe/London",
        "exchangeTimezoneShortName": "GMT",
        "gmtOffSetMilliseconds": 0,
        "market": "ccy_market",
        "esgPopulated": false,
        "marketState": "REGULAR",
        "hasPrePostMarketData": false,
        "firstTradeDateMilliseconds": 1070236800000,
        "regularMarketDayRange": "16.52 - 16.6295",
        "fullExchangeName": "CCY",
        "averageDailyVolume3Month": 0,
        "fiftyTwoWeekLowChange": 1.1281004,
        "fiftyTwoWeekLowChangePercent": 0.0731099,
        "fiftyTwoWeekRange": "15.4302 - 19.9285",
        "fiftyTwoWeekHighChangePercent": -0.16911454,
        "fiftyTwoWeekChangePercent": -11.410379,
        "fiftyDayAverageChange": -0.51800156,
        "fiftyDayAverageChangePercent": -0.030334529,
        "twoHundredDayAverageChange": -1.1333351,
        "twoHundredDayAverageChangePercent": -0.06406051,
        "sourceInterval": 15,
        "exchangeDataDelayedBy": 0,
        "cryptoTradeable": false,
        "trailingPegRatio": null
    },
    {
        "maxAge": 86400,
        "priceHint": 4,
        "previousClose": 79.4,
        "open": 79.785,
        "dayLow": 78.39,
        "dayHigh": 81.735,
        "regularMarketPreviousClose": 79.4,
        "regularMarketOpen": 79.785,
        "regularMarketDayLow": 78.39,
        "regularMarketDayHigh": 81.735,
        "volume": 0,
        "regularMarketVolume": 0,
        "averageVolume": 0,
        "averageVolume10days": 0,
        "averageDailyVolume10Day": 0,
        "bid": 80.1161,
        "ask": 80.1261,
        "bidSize": 0,
        "askSize": 0,
        "fiftyTwoWeekLow": 75.691635,
        "fiftyTwoWeekHigh": 114.999664,
        "allTimeHigh": 154.715,
        "allTimeLow": 23.071,
        "fiftyDayAverage": 79.462204,
        "twoHundredDayAverage": 80.4858,
        "currency": "RUB",
        "tradeable": false,
        "quoteType": "CURRENCY",
        "symbol": "RUB=X",
        "language": "en-US",
        "region": "US",
        "typeDisp": "Currency",
        "quoteSourceName": "Delayed Quote",
        "triggerable": true,
        "customPriceAlertConfidence": "HIGH",
        "shortName": "USD/RUB",
        "longName": "USD/RUB",
        "regularMarketChange": 0.716095,
        "regularMarketChangePercent": 0.9018828,
        "regularMarketPrice": 80.1161,
        "fiftyDayAverageChange": 0.6538925,
        "fiftyDayAverageChangePercent": 0.008228975,
        "twoHundredDayAverageChange": -0.3697052,
        "twoHundredDayAverageChangePercent": -0.0045934212,
        "sourceInterval": 15,
        "exchangeDataDelayedBy": 0,
        "cryptoTradeable": false,
        "messageBoardId": "finmb_RUB_X",
        "exchangeTimezoneName": "Europe/London",
        "exchangeTimezoneShortName": "GMT",
        "gmtOffSetMilliseconds": 0,
        "market": "ccy_market",
        "esgPopulated": false,
        "marketState": "REGULAR",
        "hasPrePostMarketData": false,
        "firstTradeDateMilliseconds": 1070236800000,
        "regularMarketDayRange": "78.39 - 81.735",
        "fullExchangeName": "CCY",
        "averageDailyVolume3Month": 0,
        "fiftyTwoWeekLowChange": 4.4244614,
        "fiftyTwoWeekLowChangePercent": 0.05845377,
        "fiftyTwoWeekRange": "75.691635 - 114.999664",
        "fiftyTwoWeekHighChange": -34.883568,
        "fiftyTwoWeekHighChangePercent": -0.30333626,
        "fiftyTwoWeekChangePercent": -30.971659,
        "corporateActions": [],
        "regularMarketTime": 1767194816,
        "exchange": "CCY",
        "trailingPegRatio": null
    }
]